Metadata-Version: 2.1
Name: libpythonpro-Adolfo
Version: 0.1
Summary: Módulo para exemplificar a construção de projetos Python no curso Pytools
Home-page: https://github.com/adolfosorato/libpythonpro
Author: Adolfo Sorato
Author-email: adolfosorato@gmail.com
License:                     GNU AFFERO GENERAL PUBLIC LICENSE
Platform: UNKNOWN
Classifier: Development Status :: 2 - Pre-Alpha
Classifier: Environment :: Console
Classifier: Intended Audience :: Developers
Classifier: License :: OSI Approved :: GNU Affero General Public License v3 or later (AGPLv3+) 
Classifier: Operating System :: OS Independent
Classifier: Programming Language :: Python
Classifier: Framework :: Pytest
License-File: LICENSE
